pystegy/__init__.py
pystegy/stegyImage.py
pystegy/utils/__init__.py
pystegy/utils/imageTool.py
pystegy/utils/tinyCrypt.py
pystegy-0.0.2.dist-info/LICENSE
pystegy-0.0.2.dist-info/METADATA
pystegy-0.0.2.dist-info/WHEEL
pystegy-0.0.2.dist-info/top_level.txt
pystegy-0.0.2.dist-info/RECORD
